{
  "resolvedId": "/var/www/html/Sueen-Nature-Frontend/node_modules/nuxt-icon/dist/runtime/Icon.vue?vue&type=style&index=0&scoped=e8d572f6&lang.css",
  "transforms": [
    {
      "name": "vite:vue",
      "result": "\n.icon {\n  display: inline-block;\n  vertical-align: middle;\n}\n",
      "start": 1727432814562,
      "end": 1727432814562
    },
    {
      "name": "nuxt:layer-aliasing",
      "start": 1727432814562,
      "end": 1727432814562,
      "order": "pre"
    },
    {
      "name": "nuxt:server-devonly:transform",
      "start": 1727432814562,
      "end": 1727432814562,
      "order": "pre"
    },
    {
      "name": "nuxt:client-fallback-auto-id",
      "start": 1727432814562,
      "end": 1727432814562,
      "order": "pre"
    },
    {
      "name": "vite:css",
      "result": ".icon{display:inline-block;vertical-align:middle}",
      "start": 1727432814562,
      "end": 1727432814574,
      "order": "normal",
      "sourcemaps": {
        "mappings": ""
      }
    },
    {
      "name": "vite:esbuild",
      "start": 1727432814574,
      "end": 1727432814574,
      "order": "normal"
    },
    {
      "name": "vite:json",
      "start": 1727432814575,
      "end": 1727432814575,
      "order": "normal"
    },
    {
      "name": "vite:worker",
      "start": 1727432814575,
      "end": 1727432814575,
      "order": "normal"
    },
    {
      "name": "vite:vue",
      "result": ".icon[data-v-e8d572f6]{display:inline-block;vertical-align:middle}",
      "start": 1727432814575,
      "end": 1727432814580,
      "order": "normal",
      "sourcemaps": {
        "mappings": ""
      }
    },
    {
      "name": "vite:vue-jsx",
      "start": 1727432814580,
      "end": 1727432814580,
      "order": "normal"
    },
    {
      "name": "replace",
      "start": 1727432814580,
      "end": 1727432814580,
      "order": "normal"
    },
    {
      "name": "nuxt:remove-plugin-metadata",
      "start": 1727432814581,
      "end": 1727432814581,
      "order": "normal"
    },
    {
      "name": "nuxt:chunk-error",
      "start": 1727432814581,
      "end": 1727432814581,
      "order": "normal"
    },
    {
      "name": "nuxt:components:imports",
      "start": 1727432814581,
      "end": 1727432814581,
      "order": "normal"
    },
    {
      "name": "replace",
      "start": 1727432814582,
      "end": 1727432814582,
      "order": "normal"
    },
    {
      "name": "ssr-styles",
      "start": 1727432814582,
      "end": 1727432814582,
      "order": "normal"
    },
    {
      "name": "vite:define",
      "start": 1727432814582,
      "end": 1727432814582,
      "order": "normal"
    },
    {
      "name": "vite:css-post",
      "result": "",
      "start": 1727432814582,
      "end": 1727432814582,
      "order": "normal",
      "sourcemaps": {
        "mappings": ""
      }
    },
    {
      "name": "vite:build-html",
      "start": 1727432814582,
      "end": 1727432814582,
      "order": "normal"
    },
    {
      "name": "vite:worker-import-meta-url",
      "start": 1727432814582,
      "end": 1727432814582,
      "order": "normal"
    },
    {
      "name": "vite:asset-import-meta-url",
      "start": 1727432814582,
      "end": 1727432814582,
      "order": "normal"
    },
    {
      "name": "commonjs",
      "start": 1727432814582,
      "end": 1727432814582,
      "order": "normal"
    },
    {
      "name": "vite:dynamic-import-vars",
      "start": 1727432814582,
      "end": 1727432814582,
      "order": "normal"
    },
    {
      "name": "vite:import-glob",
      "start": 1727432814582,
      "end": 1727432814582,
      "order": "normal"
    },
    {
      "name": "nuxt:composable-keys",
      "start": 1727432814582,
      "end": 1727432814582,
      "order": "post"
    },
    {
      "name": "nuxt:imports-transform",
      "start": 1727432814582,
      "end": 1727432814583,
      "order": "post"
    },
    {
      "name": "unctx:transform",
      "start": 1727432814583,
      "end": 1727432814583,
      "order": "post"
    },
    {
      "name": "nuxt:pages-macros-transform",
      "start": 1727432814583,
      "end": 1727432814583,
      "order": "post"
    },
    {
      "name": "nuxt:runtime-paths-dep",
      "start": 1727432814583,
      "end": 1727432814583,
      "order": "post"
    },
    {
      "name": "nuxt:route-injection-plugin",
      "start": 1727432814583,
      "end": 1727432814583,
      "order": "post"
    },
    {
      "name": "nuxt:components-loader",
      "start": 1727432814583,
      "end": 1727432814583,
      "order": "post"
    },
    {
      "name": "nuxt:tree-shake-composables:transform",
      "start": 1727432814583,
      "end": 1727432814583,
      "order": "post"
    },
    {
      "name": "vite:build-import-analysis",
      "start": 1727432814583,
      "end": 1727432814583,
      "order": "normal"
    },
    {
      "name": "vite:reporter",
      "start": 1727432814583,
      "end": 1727432814583,
      "order": "normal"
    }
  ]
}
